bcache_tools/__init__.py
bcache_tools/bcache.py
bcache_tools/bcache_super_block.py
bcache_tools/bcache_super_show.py
bcache_tools/bcache_util.py
bcache_tools/make_bcache.py
bcache_tools-0.1.dist-info/LICENSE
bcache_tools-0.1.dist-info/METADATA
bcache_tools-0.1.dist-info/WHEEL
bcache_tools-0.1.dist-info/entry_points.txt
bcache_tools-0.1.dist-info/top_level.txt
bcache_tools-0.1.dist-info/zip-safe
bcache_tools-0.1.dist-info/RECORD
