Metadata-Version: 2.1
Name: bcache-tools
Version: 0.1
Summary: The bcache command line tool developed based on python3.
Home-page: https://github.com/zoumingzhe/python-bcache-tools
Author: mingzhe
Author-email: zoumingzhe@qq.com
License: GPLv2
Project-URL: Source Code, https://github.com/zoumingzhe/python-bcache-tools
Project-URL: Bug Tracker, https://github.com/zoumingzhe/python-bcache-tools/issues
Project-URL: Documentation, https://github.com/zoumingzhe/python-bcache-tools
Keywords: bcache,bcache-tools
Platform: any
Classifier: Programming Language :: Python
Classifier: Programming Language :: Python :: 3
Classifier: Programming Language :: Python :: 3.6
Classifier: Programming Language :: Python :: 3.8
Classifier: Programming Language :: Python :: 3.10
Requires-Python: >=3.6
License-File: LICENSE
Requires-Dist: pkgconfig
Requires-Dist: pylibblkid
Requires-Dist: xarg-python
